fsai_vision_utils/__init__.py
fsai_vision_utils/clis/add_background_images.py
fsai_vision_utils/clis/aws_batch_download.py
fsai_vision_utils/clis/coco_analyze_dimensions.py
fsai_vision_utils/clis/coco_augment.py
fsai_vision_utils/clis/coco_background_crop.py
fsai_vision_utils/clis/coco_count_annotations_by_category.py
fsai_vision_utils/clis/coco_merge.py
fsai_vision_utils/clis/coco_predict.py
fsai_vision_utils/clis/coco_remap.py
fsai_vision_utils/clis/coco_resize.py
fsai_vision_utils/clis/coco_slice_dataset.py
fsai_vision_utils/clis/coco_split.py
fsai_vision_utils/clis/coco_to_yolo.py
fsai_vision_utils/clis/coco_visualize.py
fsai_vision_utils/clis/detectron_config.py
fsai_vision_utils/clis/detectron_strip.py
fsai_vision_utils/libs/__init__.py
fsai_vision_utils/libs/ensemble_model/__init__.py
fsai_vision_utils/libs/ensemble_model/ensemble_model.py
fsai_vision_utils/libs/sahi/__init__.py
fsai_vision_utils/libs/sahi/annotation.py
fsai_vision_utils/libs/sahi/models/detectron2.py
fsai_vision_utils/libs/sahi/models/ultralytics.py
fsai_vision_utils/libs/sahi/postprocess/combine.py
fsai_vision_utils/libs/sahi/predict.py
fsai_vision_utils/libs/sahi/prediction.py
fsai_vision_utils/libs/sahi/slicing.py
fsai_vision_utils/libs/sahi/utils/__init__.py
fsai_vision_utils/libs/sahi/utils/coco.py
fsai_vision_utils-0.0.261.dist-info/LICENSE
fsai_vision_utils-0.0.261.dist-info/METADATA
fsai_vision_utils-0.0.261.dist-info/WHEEL
fsai_vision_utils-0.0.261.dist-info/entry_points.txt
fsai_vision_utils-0.0.261.dist-info/RECORD
